{"annotations":[{"bbox":[567,223,428,216],"id":1,"text":"xxx","image_id":1},{"bbox":[399,447,782,222],"id":2,"text":"나는 다시","image_id":1},{"bbox":[148,665,1295,248],"id":3,"text":"꿈을 꾸기로 했다","image_id":1},{"bbox":[459,936,672,104],"id":4,"text":"xxx","image_id":1},{"bbox":[1232,984,184,84],"id":5,"text":"xxx","image_id":1}],"cropLabels":[],"images":[{"file_name":"책표지_사회과학_000904.jpg","date_created":"20210206","width":1600,"id":1,"height":1200}],"info":{"date_created":"20210206","name":"책표지_사회과학_000904","description":""},"metadata":[{"area":"","wordfont":"활자체","outline":"","illuminance":"","wordsize":"대","light":"","wordconnection":"빈공간으로 나뉨","subclass":"사회과학","weather":"","device":"스마트폰","wordcolor":"단색","class":"책표지","wordorientation":"가로"}]}