{"annotations":[{"bbox":[29,403,1557,395],"id":1,"text":"창업자 정신","image_id":1},{"bbox":[373,945,229,116],"id":2,"text":"반역성","image_id":1},{"bbox":[618,945,261,123],"id":3,"text":"현장 중시","image_id":1},{"bbox":[898,951,272,124],"id":4,"text":"xxx","image_id":1}],"cropLabels":[],"images":[{"file_name":"책표지_총류_000013.jpg","date_created":"20210218","width":1600,"id":1,"height":1200}],"info":{"date_created":"20210218","name":"책표지_총류_000013","description":""},"metadata":[{"area":"","wordfont":"활자체","outline":"","illuminance":"","wordsize":"중","light":"","wordconnection":"빈공간으로 나뉨","subclass":"총류","weather":"","device":"스마트폰","wordcolor":"단색","class":"책표지","wordorientation":"가로"}]}