{"annotations":[{"bbox":[7,557,1407,264],"id":1,"text":"세계의 식생활과","image_id":1},{"bbox":[531,853,871,264],"id":2,"text":"음식문화","image_id":1}],"cropLabels":[],"images":[{"file_name":"책표지_사회과학_005514.jpg","date_created":"20201120","width":1600,"id":1,"height":1200}],"info":{"date_created":"20210109","name":"책표지_사회과학_005514","description":""},"metadata":[{"area":"","wordfont":"활자체","outline":"","illuminance":"","wordsize":"소","light":"","wordconnection":"빈공간없이 이어짐","subclass":"사회과학","weather":"","device":"스마트폰","wordcolor":"단색","class":"책표지","wordorientation":"가로"}]}