{"annotations":[{"bbox":[164,158,1355,410],"id":1,"text":"히라도의","image_id":1},{"bbox":[463,584,705,591],"id":2,"text":"눈물","image_id":1}],"cropLabels":[],"images":[{"file_name":"책표지_문학_000162.jpg","date_created":"20210121","width":1600,"id":1,"height":1200}],"info":{"date_created":"20210121","name":"책표지_문학_000162","description":""},"metadata":[{"area":"","wordfont":"캘리그라피","outline":"","illuminance":"","wordsize":"대","light":"","wordconnection":"빈공간없이 이어짐","subclass":"문학","weather":"","device":"스마트폰","wordcolor":"단색","class":"책표지","wordorientation":"가로"}]}