{"annotations":[{"bbox":[434,194,685,295],"id":1,"text":"당신의","image_id":1},{"bbox":[339,495,912,247],"id":2,"text":"그 미소가","image_id":1},{"bbox":[441,742,806,304],"id":3,"text":"좋아서","image_id":1},{"bbox":[709,0,89,70],"id":4,"text":"xxx","image_id":1},{"bbox":[893,0,707,54],"id":5,"text":"xxx","image_id":1}],"cropLabels":[],"images":[{"file_name":"책표지_기술과학_003882.jpg","date_created":"20210207","width":1600,"id":1,"height":1200}],"info":{"date_created":"20210207","name":"책표지_기술과학_003882","description":""},"metadata":[{"area":"","wordfont":"활자체","outline":"","illuminance":"","wordsize":"중","light":"","wordconnection":"빈공간으로 나뉨","subclass":"기술과학","weather":"","device":"스마트폰","wordcolor":"단색","class":"책표지","wordorientation":"가로"}]}