{"annotations":[{"bbox":[362,187,567,332],"id":1,"text":"한국","image_id":1},{"bbox":[349,530,586,311],"id":2,"text":"전통","image_id":1},{"bbox":[337,851,597,341],"id":3,"text":"가구","image_id":1}],"cropLabels":[],"images":[{"file_name":"책표지_예술_000664.jpg","date_created":"20210210","width":1600,"id":1,"height":1200}],"info":{"date_created":"20210210","name":"책표지_예술_000664","description":""},"metadata":[{"area":"","wordfont":"활자체","outline":"","illuminance":"","wordsize":"중","light":"","wordconnection":"빈공간없이 이어짐","subclass":"예술","weather":"","device":"스마트폰","wordcolor":"단색","class":"책표지","wordorientation":"가로"}]}