{"annotations":[{"bbox":[10,513,848,320],"id":1,"text":"만다라","image_id":1},{"bbox":[858,485,722,299],"id":2,"text":"이야기","image_id":1},{"bbox":[79,854,1314,214],"id":3,"text":"xxx","image_id":1}],"cropLabels":[],"images":[{"file_name":"책표지_예술_000456.JPG","date_created":"20210203","width":1600,"id":1,"height":1200}],"info":{"date_created":"20210203","name":"책표지_예술_000456","description":""},"metadata":[{"area":"","wordfont":"활자체","outline":"","illuminance":"","wordsize":"소","light":"","wordconnection":"빈공간없이 이어짐","subclass":"예술","weather":"","device":"스마트폰","wordcolor":"단색","class":"책표지","wordorientation":"가로"}]}