{"annotations":[{"bbox":[177,147,849,330],"id":1,"text":"예술과","image_id":1},{"bbox":[181,486,394,301],"id":2,"text":"그 ","image_id":1},{"bbox":[179,813,622,345],"id":3,"text":"가치","image_id":1}],"cropLabels":[],"images":[{"file_name":"책표지_예술_001886.JPG","date_created":"20210128","width":1600,"id":1,"height":1200}],"info":{"date_created":"20210128","name":"책표지_예술_001886","description":""},"metadata":[{"area":"","wordfont":"활자체","outline":"","illuminance":"","wordsize":"중","light":"","wordconnection":"빈공간없이 이어짐","subclass":"예술","weather":"","device":"스마트폰","wordcolor":"단색","class":"책표지","wordorientation":"가로"}]}