{"annotations":[{"bbox":[582,767,410,273],"id":1,"text":"사전","image_id":1},{"bbox":[672,1064,397,84],"id":2,"text":"xxx","image_id":1},{"bbox":[519,23,582,765],"id":3,"text":"xxx","image_id":1},{"bbox":[0,0,212,1200],"id":4,"text":"xxx","image_id":1},{"bbox":[1513,0,87,1200],"id":5,"text":"xxx","image_id":1}],"cropLabels":[],"images":[{"file_name":"책표지_기술과학_006198.jpg","date_created":"20210214","width":1600,"id":1,"height":1200}],"info":{"date_created":"20210214","name":"책표지_기술과학_006198","description":""},"metadata":[{"area":"","wordfont":"활자체","outline":"","illuminance":"","wordsize":"소","light":"","wordconnection":"빈공간없이 이어짐","subclass":"기술과학","weather":"","device":"스마트폰","wordcolor":"단색","class":"책표지","wordorientation":"가로"}]}