{"annotations":[{"bbox":[456,168,998,374],"id":1,"text":"세계사","image_id":1},{"bbox":[906,534,518,273],"id":2,"text":"강의","image_id":1},{"bbox":[579,9,811,148],"id":3,"text":"xxx","image_id":1},{"bbox":[598,745,7,4],"id":4,"text":"xxx","image_id":1},{"bbox":[267,731,627,73],"id":5,"text":"xxx","image_id":1},{"bbox":[683,878,338,75],"id":6,"text":"xxx","image_id":1},{"bbox":[891,1130,533,70],"id":7,"text":"xxx","image_id":1}],"cropLabels":[],"images":[{"file_name":"책표지_자연과학_001509.jpg","date_created":"20210201","width":1600,"id":1,"height":1200}],"info":{"date_created":"20210201","name":"책표지_자연과학_001509","description":""},"metadata":[{"area":"","wordfont":"활자체","outline":"","illuminance":"","wordsize":"대","light":"","wordconnection":"빈공간으로 나뉨","subclass":"자연과학","weather":"","device":"스마트폰","wordcolor":"단색","class":"책표지","wordorientation":"가로"}]}