{"annotations":[{"bbox":[634,31,390,313],"id":1,"text":"오","image_id":1},{"bbox":[761,378,313,390],"id":2,"text":"리","image_id":1},{"bbox":[662,768,352,384],"id":3,"text":"진","image_id":1},{"bbox":[472,431,53,769],"id":4,"text":"xxx","image_id":1}],"cropLabels":[],"images":[{"file_name":"책표지_자연과학_000708.jpg","date_created":"20210130","width":1600,"id":1,"height":1200}],"info":{"date_created":"20210130","name":"책표지_자연과학_000708","description":""},"metadata":[{"area":"","wordfont":"활자체","outline":"","illuminance":"","wordsize":"중","light":"","wordconnection":"빈공간없이 이어짐","subclass":"자연과학","weather":"","device":"스마트폰","wordcolor":"단색","class":"책표지","wordorientation":"세로"}]}