{"annotations":[{"bbox":[471,270,255,180],"id":1,"text":"미","image_id":1},{"bbox":[942,236,248,209],"id":2,"text":"치","image_id":1},{"bbox":[1192,238,253,251],"id":3,"text":"료","image_id":1},{"bbox":[522,69,875,144],"id":4,"text":"xxx","image_id":1},{"bbox":[725,216,252,381],"id":5,"text":"xxx","image_id":1},{"bbox":[843,586,644,113],"id":6,"text":"xxx","image_id":1}],"cropLabels":[],"images":[{"file_name":"책표지_기술과학_006045.jpg","date_created":"20210213","width":1600,"id":1,"height":1200}],"info":{"date_created":"20210213","name":"책표지_기술과학_006045","description":""},"metadata":[{"area":"","wordfont":"캘리그라피","outline":"","illuminance":"","wordsize":"소","light":"","wordconnection":"빈공간없이 이어짐","subclass":"기술과학","weather":"","device":"스마트폰","wordcolor":"단색","class":"책표지","wordorientation":"가로"}]}