{"annotations":[{"bbox":[201,81,731,133],"id":1,"text":"xxx","image_id":1},{"bbox":[932,96,312,113],"id":2,"text":"패션 액세서리","image_id":1},{"bbox":[1259,114,94,98],"id":3,"text":"xxx","image_id":1},{"bbox":[60,225,1022,210],"id":4,"text":"귀여운 액세서리","image_id":1},{"bbox":[1081,227,363,211],"id":5,"text":"만들기","image_id":1},{"bbox":[508,495,648,128],"id":6,"text":"xxx","image_id":1}],"cropLabels":[],"images":[{"file_name":"책표지_기술과학_001715.jpg","date_created":"20210206","width":1600,"id":1,"height":1200}],"info":{"date_created":"20210206","name":"책표지_기술과학_001715","description":""},"metadata":[{"area":"","wordfont":"활자체","outline":"","illuminance":"","wordsize":"중","light":"","wordconnection":"빈공간으로 나뉨","subclass":"기술과학","weather":"","device":"스마트폰","wordcolor":"단색","class":"책표지","wordorientation":"가로"}]}