{"annotations":[{"bbox":[348,86,686,135],"id":1,"text":"xxx","image_id":1},{"bbox":[366,215,695,287],"id":2,"text":"프랑스어","image_id":1},{"bbox":[359,504,705,683],"id":3,"text":"xxx","image_id":1},{"bbox":[155,846,388,102],"id":4,"text":"xxx","image_id":1},{"bbox":[284,997,255,52],"id":5,"text":"xxx","image_id":1},{"bbox":[0,1020,148,180],"id":6,"text":"xxx","image_id":1}],"cropLabels":[],"images":[{"file_name":"책표지_언어_001109.jpg","date_created":"20210207","width":1600,"id":1,"height":1200}],"info":{"date_created":"20210207","name":"책표지_언어_001109","description":""},"metadata":[{"area":"","wordfont":"캘리그라피","outline":"","illuminance":"","wordsize":"대","light":"","wordconnection":"빈공간없이 이어짐","subclass":"언어","weather":"","device":"스마트폰","wordcolor":"단색","class":"책표지","wordorientation":"가로"}]}