{"annotations":[{"bbox":[306,112,1041,219],"id":1,"text":"교회를 깨우는","image_id":1},{"bbox":[276,337,1095,433],"id":2,"text":"한밤의","image_id":1},{"bbox":[434,769,747,403],"id":3,"text":"외침","image_id":1}],"cropLabels":[],"images":[{"file_name":"책표지_종교_001009.jpg","date_created":"20210123","width":1600,"id":1,"height":1200}],"info":{"date_created":"20210123","name":"책표지_종교_001009","description":""},"metadata":[{"area":"","wordfont":"활자체","outline":"","illuminance":"","wordsize":"대","light":"","wordconnection":"빈공간으로 나뉨","subclass":"종교","weather":"","device":"스마트폰","wordcolor":"단색","class":"책표지","wordorientation":"가로"}]}