{"annotations":[{"bbox":[450,98,304,128],"id":1,"text":"팻 메시니","image_id":1},{"bbox":[782,108,567,107],"id":2,"text":"리처드 나일즈 대담","image_id":1},{"bbox":[604,388,589,186],"id":3,"text":"팻 메시니","image_id":1}],"cropLabels":[],"images":[{"file_name":"책표지_예술_001904.jpg","date_created":"20210127","width":1600,"id":1,"height":1200}],"info":{"date_created":"20210127","name":"책표지_예술_001904","description":""},"metadata":[{"area":"","wordfont":"활자체","outline":"","illuminance":"","wordsize":"소","light":"","wordconnection":"빈공간으로 나뉨","subclass":"예술","weather":"","device":"스마트폰","wordcolor":"단색","class":"책표지","wordorientation":"가로"}]}