{"annotations":[{"bbox":[830,43,149,398],"id":1,"text":"명화는","image_id":1},{"bbox":[844,455,119,256],"id":2,"text":"스스로","image_id":1},{"bbox":[830,719,159,443],"id":3,"text":"말한다","image_id":1}],"cropLabels":[],"images":[{"file_name":"책표지_예술_000580.jpg","date_created":"20210201","width":1600,"id":1,"height":1200}],"info":{"date_created":"20210201","name":"책표지_예술_000580","description":""},"metadata":[{"area":"","wordfont":"활자체","outline":"","illuminance":"","wordsize":"소","light":"","wordconnection":"빈공간으로 나뉨","subclass":"예술","weather":"","device":"스마트폰","wordcolor":"여러색","class":"책표지","wordorientation":"세로"}]}