{"annotations":[{"bbox":[631,591,949,219],"id":1,"text":"무서운 그림","image_id":1},{"bbox":[624,836,569,126],"id":2,"text":"매혹과 반전의 ","image_id":1},{"bbox":[1223,829,356,119],"id":3,"text":"명화 읽기","image_id":1}],"cropLabels":[],"images":[{"file_name":"책표지_예술_000986.JPG","date_created":"20210202","width":1600,"id":1,"height":1200}],"info":{"date_created":"20210202","name":"책표지_예술_000986","description":""},"metadata":[{"area":"","wordfont":"활자체","outline":"","illuminance":"","wordsize":"소","light":"","wordconnection":"빈공간으로 나뉨","subclass":"예술","weather":"","device":"스마트폰","wordcolor":"단색","class":"책표지","wordorientation":"가로"}]}