{"annotations":[{"bbox":[238,322,972,679],"id":1,"text":"한 달에 한 도시","image_id":1},{"bbox":[279,89,653,122],"id":2,"text":"에어비앤비로 여행하기","image_id":1},{"bbox":[963,109,237,99],"id":3,"text":"남미편","image_id":1},{"bbox":[289,1106,199,94],"id":4,"text":"xxx","image_id":1},{"bbox":[514,1121,200,79],"id":5,"text":"xxx","image_id":1}],"cropLabels":[],"images":[{"file_name":"책표지_기타_003245.JPG","date_created":"20210119","width":1600,"id":1,"height":1200}],"info":{"date_created":"20210119","name":"책표지_기타_003245","description":""},"metadata":[{"area":"","wordfont":"활자체","outline":"","illuminance":"","wordsize":"대","light":"","wordconnection":"빈공간으로 나뉨","subclass":"기타","weather":"","device":"스마트폰","wordcolor":"단색","class":"책표지","wordorientation":"가로"}]}