{"annotations":[{"bbox":[74,163,461,250],"id":1,"text":"안드","image_id":1},{"bbox":[52,414,772,276],"id":2,"text":"모든 것","image_id":1},{"bbox":[70,700,1192,304],"id":3,"text":"분석과 포팅","image_id":1},{"bbox":[82,1038,1219,162],"id":4,"text":"xxx","image_id":1},{"bbox":[540,149,923,249],"id":5,"text":"xxx","image_id":1}],"cropLabels":[],"images":[{"file_name":"책표지_기술과학_000959.jpg","date_created":"20210205","width":1600,"id":1,"height":1200}],"info":{"date_created":"20210205","name":"책표지_기술과학_000959","description":""},"metadata":[{"area":"","wordfont":"활자체","outline":"","illuminance":"","wordsize":"소","light":"","wordconnection":"빈공간으로 나뉨","subclass":"기술과학","weather":"","device":"스마트폰","wordcolor":"단색","class":"책표지","wordorientation":"가로"}]}