{"annotations":[{"bbox":[172,103,694,285],"id":1,"text":"서울의","image_id":1},{"bbox":[177,470,1290,282],"id":2,"text":"다섯 궁궐과","image_id":1},{"bbox":[167,856,263,227],"id":3,"text":"xxx","image_id":1},{"bbox":[495,836,452,267],"id":4,"text":"앞길","image_id":1}],"cropLabels":[],"images":[{"file_name":"책표지_기술과학_001761.jpg","date_created":"20210206","width":1600,"id":1,"height":1200}],"info":{"date_created":"20210206","name":"책표지_기술과학_001761","description":""},"metadata":[{"area":"","wordfont":"활자체","outline":"","illuminance":"","wordsize":"중","light":"","wordconnection":"빈공간으로 나뉨","subclass":"기술과학","weather":"","device":"스마트폰","wordcolor":"단색","class":"책표지","wordorientation":"가로"}]}