{"annotations":[{"bbox":[0,87,243,161],"id":1,"text":"xxx","image_id":1},{"bbox":[1348,723,159,85],"id":2,"text":"xxx","image_id":1},{"bbox":[73,279,620,350],"id":3,"text":"동글동글","image_id":1},{"bbox":[691,186,861,476],"id":4,"text":"동그라미","image_id":1}],"cropLabels":[],"images":[{"file_name":"책표지_기타_002643.jpg","date_created":"20210121","width":1600,"id":1,"height":1200}],"info":{"date_created":"20210121","name":"책표지_기타_002643","description":""},"metadata":[{"area":"","wordfont":"캘리그라피","outline":"","illuminance":"","wordsize":"중","light":"","wordconnection":"빈공간없이 이어짐","subclass":"기타","weather":"","device":"스마트폰","wordcolor":"여러색","class":"책표지","wordorientation":"가로"}]}