{"annotations":[{"bbox":[27,22,1411,325],"id":1,"text":"생각 버리기 연습","image_id":1},{"bbox":[31,427,651,115],"id":2,"text":"복잡하 생각을 잠재우는","image_id":1},{"bbox":[35,545,596,98],"id":3,"text":"행복한 마음 다스리기","image_id":1},{"bbox":[1326,493,274,165],"id":4,"text":"xxx","image_id":1}],"cropLabels":[],"images":[{"file_name":"책표지_기타_001815.jpg","date_created":"20210125","width":1600,"id":1,"height":1200}],"info":{"date_created":"20210125","name":"책표지_기타_001815","description":""},"metadata":[{"area":"","wordfont":"활자체","outline":"","illuminance":"","wordsize":"중","light":"","wordconnection":"빈공간으로 나뉨","subclass":"기타","weather":"","device":"스마트폰","wordcolor":"단색","class":"책표지","wordorientation":"가로"}]}