{"annotations":[{"bbox":[156,76,380,317],"id":1,"text":"누구","image_id":1},{"bbox":[536,208,573,167],"id":2,"text":"에게나","image_id":1},{"bbox":[131,381,1305,448],"id":3,"text":"xxx","image_id":1},{"bbox":[1116,319,255,145],"id":4,"text":"xxx","image_id":1}],"cropLabels":[],"images":[{"file_name":"책표지_문학_001559.jpg","date_created":"20210127","width":1600,"id":1,"height":1200}],"info":{"date_created":"20210127","name":"책표지_문학_001559","description":""},"metadata":[{"area":"","wordfont":"캘리그라피","outline":"","illuminance":"","wordsize":"중","light":"","wordconnection":"빈공간없이 이어짐","subclass":"문학","weather":"","device":"스마트폰","wordcolor":"단색","class":"책표지","wordorientation":"가로"}]}