{"annotations":[{"bbox":[217,183,1216,426],"id":1,"text":"사랑은","image_id":1},{"bbox":[37,648,1539,421],"id":2,"text":"오프비트","image_id":1}],"cropLabels":[],"images":[{"file_name":"책표지_문학_001672.jpg","date_created":"20210215","width":1600,"id":1,"height":1200}],"info":{"date_created":"20210215","name":"책표지_문학_001672","description":""},"metadata":[{"area":"","wordfont":"활자체","outline":"","illuminance":"","wordsize":"대","light":"","wordconnection":"빈공간없이 이어짐","subclass":"문학","weather":"","device":"스마트폰","wordcolor":"여러색","class":"책표지","wordorientation":"가로"}]}