{"annotations":[{"bbox":[527,193,250,276],"id":1,"text":"xxx","image_id":1},{"bbox":[780,59,172,246],"id":2,"text":"xxx","image_id":1},{"bbox":[950,241,392,246],"id":3,"text":"xxx","image_id":1},{"bbox":[504,497,857,264],"id":4,"text":"마음편한 ","image_id":1},{"bbox":[539,1073,168,72],"id":5,"text":"xxx","image_id":1},{"bbox":[709,1071,228,70],"id":6,"text":"xxx","image_id":1},{"bbox":[977,1064,345,74],"id":7,"text":"xxx","image_id":1},{"bbox":[507,767,255,294],"id":8,"text":"인","image_id":1},{"bbox":[764,828,557,215],"id":9,"text":"생선택","image_id":1},{"bbox":[890,1171,90,29],"id":10,"text":"xxx","image_id":1}],"cropLabels":[],"images":[{"file_name":"책표지_사회과학_004821.JPG","date_created":"20210215","width":1600,"id":1,"height":1200}],"info":{"date_created":"20210215","name":"책표지_사회과학_004821","description":""},"metadata":[{"area":"","wordfont":"활자체","outline":"","illuminance":"","wordsize":"소","light":"","wordconnection":"빈공간없이 이어짐","subclass":"사회과학","weather":"","device":"스마트폰","wordcolor":"단색","class":"책표지","wordorientation":"가로"}]}