{"annotations":[{"bbox":[530,438,388,148],"id":1,"text":"멈추지 마","image_id":1},{"bbox":[530,615,578,155],"id":2,"text":"다시 꿈부터","image_id":1},{"bbox":[530,797,766,234],"id":3,"text":"xxx","image_id":1},{"bbox":[1058,1092,216,73],"id":4,"text":"xxx","image_id":1},{"bbox":[1305,668,295,225],"id":5,"text":"xxx","image_id":1},{"bbox":[703,150,426,169],"id":6,"text":"xxx","image_id":1},{"bbox":[8,51,440,1149],"id":7,"text":"xxx","image_id":1},{"bbox":[921,542,23,38],"id":8,"text":"xxx","image_id":1}],"cropLabels":[],"images":[{"file_name":"책표지_문학_006721.jpg","date_created":"20210206","width":1600,"id":1,"height":1200}],"info":{"date_created":"20210206","name":"책표지_문학_006721","description":""},"metadata":[{"area":"","wordfont":"활자체","outline":"","illuminance":"","wordsize":"중","light":"","wordconnection":"빈공간없이 이어짐","subclass":"문학","weather":"","device":"스마트폰","wordcolor":"단색","class":"책표지","wordorientation":"가로"}]}