{"annotations":[{"bbox":[49,157,286,128],"id":1,"text":"수정판","image_id":1},{"bbox":[39,354,1311,191],"id":2,"text":"중국 고대사회의 형성","image_id":1},{"bbox":[47,589,1469,499],"id":3,"text":"사마천 사기","image_id":1}],"cropLabels":[],"images":[{"file_name":"책표지_역사_000038.jpg","date_created":"20210122","width":1600,"id":1,"height":1200}],"info":{"date_created":"20210122","name":"책표지_역사_000038","description":""},"metadata":[{"area":"","wordfont":"활자체","outline":"","illuminance":"","wordsize":"중","light":"","wordconnection":"빈공간없이 이어짐","subclass":"역사","weather":"","device":"스마트폰","wordcolor":"여러색","class":"책표지","wordorientation":"가로"}]}