{"annotations":[{"bbox":[17,493,1514,312],"id":1,"text":"사생활의 천재들","image_id":1},{"bbox":[593,816,391,156],"id":2,"text":"정혜윤","image_id":1},{"bbox":[621,980,399,106],"id":3,"text":"xxx","image_id":1},{"bbox":[1013,963,302,114],"id":4,"text":"xxx","image_id":1},{"bbox":[1353,973,187,73],"id":5,"text":"xxx","image_id":1}],"cropLabels":[],"images":[{"file_name":"책표지_기타_002049.jpg","date_created":"20210126","width":1600,"id":1,"height":1200}],"info":{"date_created":"20210126","name":"책표지_기타_002049","description":""},"metadata":[{"area":"","wordfont":"활자체","outline":"","illuminance":"","wordsize":"대","light":"","wordconnection":"빈공간으로 나뉨","subclass":"기타","weather":"","device":"스마트폰","wordcolor":"여러색","class":"책표지","wordorientation":"가로"}]}