{"annotations":[{"bbox":[383,289,776,163],"id":1,"text":"동백주 몇 잔에 ","image_id":1},{"bbox":[399,699,453,153],"id":2,"text":"서동인 시집","image_id":1},{"bbox":[405,458,614,148],"id":3,"text":"꽃이 피다니","image_id":1}],"cropLabels":[],"images":[{"file_name":"책표지_문학_002848.jpeg","date_created":"20210131","width":1600,"id":1,"height":1200}],"info":{"date_created":"20210131","name":"책표지_문학_002848","description":""},"metadata":[{"area":"","wordfont":"활자체","outline":"","illuminance":"","wordsize":"소","light":"","wordconnection":"빈공간없이 이어짐","subclass":"문학","weather":"","device":"스마트폰","wordcolor":"여러색","class":"책표지","wordorientation":"가로"}]}