{"annotations":[{"bbox":[42,321,1281,364],"id":1,"text":"초인수업","image_id":1},{"bbox":[117,691,552,155],"id":2,"text":"나를 넘어","image_id":1},{"bbox":[687,688,630,185],"id":3,"text":"나를 만나다","image_id":1}],"cropLabels":[],"images":[{"file_name":"책표지_철학_001106.jpg","date_created":"20210210","width":1600,"id":1,"height":1200}],"info":{"date_created":"20210210","name":"책표지_철학_001106","description":""},"metadata":[{"area":"","wordfont":"활자체","outline":"","illuminance":"","wordsize":"중","light":"","wordconnection":"빈공간으로 나뉨","subclass":"철학","weather":"","device":"스마트폰","wordcolor":"단색","class":"책표지","wordorientation":"가로"}]}