{"annotations":[{"bbox":[123,321,742,321],"id":1,"text":"에너지","image_id":1},{"bbox":[858,294,728,318],"id":2,"text":"인터넷","image_id":1},{"bbox":[884,608,684,287],"id":3,"text":"시스템","image_id":1},{"bbox":[931,975,615,225],"id":4,"text":"xxx","image_id":1}],"cropLabels":[],"images":[{"file_name":"책표지_사회과학_000038.jpg","date_created":"20210209","width":1600,"id":1,"height":1200}],"info":{"date_created":"20210209","name":"책표지_사회과학_000038","description":""},"metadata":[{"area":"","wordfont":"활자체","outline":"","illuminance":"","wordsize":"중","light":"","wordconnection":"빈공간없이 이어짐","subclass":"사회과학","weather":"","device":"스마트폰","wordcolor":"여러색","class":"책표지","wordorientation":"가로"}]}