{"annotations":[{"bbox":[130,369,660,308],"id":1,"text":"설득의","image_id":1},{"bbox":[806,378,702,295],"id":2,"text":"심리학","image_id":1},{"bbox":[521,695,122,60],"id":3,"text":"로버트","image_id":1},{"bbox":[646,698,145,61],"id":4,"text":"xxx","image_id":1},{"bbox":[793,703,80,59],"id":5,"text":"xxx","image_id":1},{"bbox":[903,701,116,71],"id":6,"text":"xxx","image_id":1},{"bbox":[1027,703,82,66],"id":7,"text":"xxx","image_id":1},{"bbox":[612,14,176,100],"id":8,"text":"xxx","image_id":1},{"bbox":[798,22,177,99],"id":9,"text":"xxx","image_id":1},{"bbox":[980,22,231,99],"id":10,"text":"xxx","image_id":1},{"bbox":[1242,14,127,105],"id":11,"text":"xxx","image_id":1},{"bbox":[1371,19,169,120],"id":12,"text":"xxx","image_id":1},{"bbox":[1548,32,52,87],"id":13,"text":"xxx","image_id":1}],"cropLabels":[],"images":[{"file_name":"책표지_사회과학_000115.jpg","date_created":"20210206","width":1600,"id":1,"height":1200}],"info":{"date_created":"20210206","name":"책표지_사회과학_000115","description":""},"metadata":[{"area":"","wordfont":"활자체","outline":"","illuminance":"","wordsize":"중","light":"","wordconnection":"빈공간없이 이어짐","subclass":"사회과학","weather":"","device":"스마트폰","wordcolor":"단색","class":"책표지","wordorientation":"가로"}]}