{"annotations":[{"bbox":[414,21,696,272],"id":1,"text":"돼지도","image_id":1},{"bbox":[290,291,944,263],"id":2,"text":"장난감이","image_id":1},{"bbox":[424,556,675,258],"id":3,"text":"xxx","image_id":1},{"bbox":[674,836,201,65],"id":4,"text":"xxx","image_id":1},{"bbox":[691,995,158,98],"id":5,"text":"xxx","image_id":1},{"bbox":[996,811,277,57],"id":6,"text":"xxx","image_id":1},{"bbox":[104,794,290,267],"id":7,"text":"xxx","image_id":1}],"cropLabels":[],"images":[{"file_name":"책표지_기술과학_002483.jpg","date_created":"20210207","width":1600,"id":1,"height":1200}],"info":{"date_created":"20210207","name":"책표지_기술과학_002483","description":""},"metadata":[{"area":"","wordfont":"활자체","outline":"","illuminance":"","wordsize":"소","light":"","wordconnection":"빈공간없이 이어짐","subclass":"기술과학","weather":"","device":"스마트폰","wordcolor":"단색","class":"책표지","wordorientation":"가로"}]}