{"annotations":[{"bbox":[46,144,869,122],"id":1,"text":"하늘을 감동시켜","image_id":1},{"bbox":[318,266,604,134],"id":2,"text":"서천에 오른 ","image_id":1},{"bbox":[941,122,622,286],"id":3,"text":"욱면","image_id":1}],"cropLabels":[],"images":[{"file_name":"책표지_문학_005309.jpg","date_created":"20210128","width":1600,"id":1,"height":1200}],"info":{"date_created":"20210128","name":"책표지_문학_005309","description":""},"metadata":[{"area":"","wordfont":"활자체","outline":"","illuminance":"","wordsize":"소","light":"","wordconnection":"빈공간으로 나뉨","subclass":"문학","weather":"","device":"스마트폰","wordcolor":"단색","class":"책표지","wordorientation":"가로"}]}