{"annotations":[{"bbox":[562,512,669,320],"id":1,"text":"유머","image_id":1},{"bbox":[277,829,984,330],"id":2,"text":"세일즈","image_id":1},{"bbox":[164,388,550,113],"id":3,"text":"웃게 할 수 있다면","image_id":1},{"bbox":[4,616,169,88],"id":4,"text":"xxx","image_id":1},{"bbox":[717,388,467,109],"id":5,"text":"xxx","image_id":1}],"cropLabels":[],"images":[{"file_name":"책표지_총류_000981.jpg","date_created":"20210218","width":1600,"id":1,"height":1200}],"info":{"date_created":"20210218","name":"책표지_총류_000981","description":""},"metadata":[{"area":"","wordfont":"활자체","outline":"","illuminance":"","wordsize":"중","light":"","wordconnection":"빈공간으로 나뉨","subclass":"총류","weather":"","device":"스마트폰","wordcolor":"단색","class":"책표지","wordorientation":"가로"}]}