{"annotations":[{"bbox":[226,57,586,700],"id":1,"text":"혼","image_id":1},{"bbox":[409,763,779,218],"id":2,"text":"초등영문법","image_id":1},{"bbox":[634,988,462,208],"id":3,"text":"xxx","image_id":1},{"bbox":[809,168,451,583],"id":4,"text":"xxx","image_id":1}],"cropLabels":[],"images":[{"file_name":"책표지_언어_001016.jpg","date_created":"20210205","width":1600,"id":1,"height":1200}],"info":{"date_created":"20210205","name":"책표지_언어_001016","description":""},"metadata":[{"area":"","wordfont":"활자체","outline":"","illuminance":"","wordsize":"대","light":"","wordconnection":"빈공간없이 이어짐","subclass":"언어","weather":"","device":"스마트폰","wordcolor":"단색","class":"책표지","wordorientation":"가로"}]}