{"annotations":[{"bbox":[293,151,913,269],"id":1,"text":"시월드에서","image_id":1},{"bbox":[292,443,997,246],"id":2,"text":"쿨한여자로","image_id":1},{"bbox":[290,710,665,278],"id":3,"text":"살겠다","image_id":1},{"bbox":[335,1006,269,94],"id":4,"text":"xxx","image_id":1},{"bbox":[619,1004,204,97],"id":5,"text":"xxx","image_id":1},{"bbox":[846,1004,477,101],"id":6,"text":"xxx","image_id":1},{"bbox":[324,1118,312,62],"id":7,"text":"xxx","image_id":1},{"bbox":[666,1119,242,71],"id":8,"text":"xxx","image_id":1}],"cropLabels":[],"images":[{"file_name":"책표지_사회과학_004010.jpg","date_created":"20210127","width":1600,"id":1,"height":1200}],"info":{"date_created":"20210127","name":"책표지_사회과학_004010","description":""},"metadata":[{"area":"","wordfont":"활자체","outline":"","illuminance":"","wordsize":"대","light":"","wordconnection":"빈공간없이 이어짐","subclass":"사회과학","weather":"","device":"스마트폰","wordcolor":"단색","class":"책표지","wordorientation":"가로"}]}