{"annotations":[{"bbox":[85,236,887,184],"id":1,"text":"유태종 박사의","image_id":1},{"bbox":[85,426,1333,343],"id":2,"text":"건강 장수법","image_id":1},{"bbox":[905,877,451,136],"id":3,"text":"xxx","image_id":1},{"bbox":[1110,3,316,82],"id":4,"text":"xxx","image_id":1}],"cropLabels":[],"images":[{"file_name":"책표지_기술과학_003019.JPG","date_created":"20210207","width":1600,"id":1,"height":1200}],"info":{"date_created":"20210207","name":"책표지_기술과학_003019","description":""},"metadata":[{"area":"","wordfont":"활자체","outline":"","illuminance":"","wordsize":"중","light":"","wordconnection":"빈공간으로 나뉨","subclass":"기술과학","weather":"","device":"스마트폰","wordcolor":"단색","class":"책표지","wordorientation":"가로"}]}