{"annotations":[{"bbox":[229,373,1244,374],"id":1,"text":"일 잘하는 사람은","image_id":1},{"bbox":[120,745,874,426],"id":2,"text":"알기쉽게","image_id":1},{"bbox":[997,750,572,420],"id":3,"text":"말한다","image_id":1},{"bbox":[338,229,419,111],"id":4,"text":"xxx","image_id":1},{"bbox":[764,229,272,109],"id":5,"text":"xxx","image_id":1},{"bbox":[1081,230,277,111],"id":6,"text":"xxx","image_id":1}],"cropLabels":[],"images":[{"file_name":"책표지_사회과학_000126.jpg","date_created":"20210206","width":1600,"id":1,"height":1200}],"info":{"date_created":"20210206","name":"책표지_사회과학_000126","description":""},"metadata":[{"area":"","wordfont":"캘리그라피","outline":"","illuminance":"","wordsize":"중","light":"","wordconnection":"빈공간으로 나뉨","subclass":"사회과학","weather":"","device":"스마트폰","wordcolor":"단색","class":"책표지","wordorientation":"가로"}]}