{"annotations":[{"bbox":[320,179,299,377],"id":1,"text":"일","image_id":1},{"bbox":[536,555,205,178],"id":2,"text":"xxx","image_id":1},{"bbox":[562,710,729,93],"id":3,"text":"xxx","image_id":1},{"bbox":[918,513,192,197],"id":4,"text":"버","image_id":1},{"bbox":[920,152,272,343],"id":5,"text":"트","image_id":1},{"bbox":[1190,151,278,417],"id":6,"text":"xxx","image_id":1},{"bbox":[619,159,299,398],"id":7,"text":"xxx","image_id":1},{"bbox":[743,533,172,184],"id":8,"text":"xxx","image_id":1},{"bbox":[1110,536,179,177],"id":9,"text":"xxx","image_id":1}],"cropLabels":[],"images":[{"file_name":"책표지_자연과학_001053.jpg","date_created":"20210208","width":1600,"id":1,"height":1200}],"info":{"date_created":"20210208","name":"책표지_자연과학_001053","description":""},"metadata":[{"area":"","wordfont":"캘리그라피","outline":"","illuminance":"","wordsize":"소","light":"","wordconnection":"빈공간없이 이어짐","subclass":"자연과학","weather":"","device":"스마트폰","wordcolor":"단색","class":"책표지","wordorientation":"가로"}]}