{"annotations":[{"bbox":[96,366,1504,317],"id":1,"text":"장사를 했으면","image_id":1},{"bbox":[0,686,1453,346],"id":2,"text":"이익을 내라","image_id":1},{"bbox":[1397,888,153,128],"id":3,"text":"xxx","image_id":1},{"bbox":[288,274,559,102],"id":4,"text":"xxx","image_id":1},{"bbox":[840,244,675,147],"id":5,"text":"xxx","image_id":1},{"bbox":[75,144,257,84],"id":6,"text":"xxx","image_id":1}],"cropLabels":[],"images":[{"file_name":"책표지_사회과학_004051.jpg","date_created":"20210128","width":1600,"id":1,"height":1200}],"info":{"date_created":"20210128","name":"책표지_사회과학_004051","description":""},"metadata":[{"area":"","wordfont":"활자체","outline":"","illuminance":"","wordsize":"대","light":"","wordconnection":"빈공간으로 나뉨","subclass":"사회과학","weather":"","device":"스마트폰","wordcolor":"단색","class":"책표지","wordorientation":"가로"}]}