{"annotations":[{"bbox":[418,230,894,358],"id":1,"text":"닥치고","image_id":1},{"bbox":[281,611,552,329],"id":2,"text":"군대","image_id":1},{"bbox":[884,588,603,340],"id":3,"text":"육아","image_id":1},{"bbox":[0,614,88,76],"id":4,"text":"xxx","image_id":1}],"cropLabels":[],"images":[{"file_name":"책표지_기술과학_004039.jpg","date_created":"20210207","width":1600,"id":1,"height":1200}],"info":{"date_created":"20210207","name":"책표지_기술과학_004039","description":""},"metadata":[{"area":"","wordfont":"활자체","outline":"","illuminance":"","wordsize":"중","light":"","wordconnection":"빈공간없이 이어짐","subclass":"기술과학","weather":"","device":"스마트폰","wordcolor":"단색","class":"책표지","wordorientation":"가로"}]}