{"annotations":[{"bbox":[376,731,861,138],"id":1,"text":"xxx","image_id":1},{"bbox":[31,883,814,266],"id":2,"text":"명문학벌","image_id":1},{"bbox":[866,925,637,219],"id":3,"text":"안 부럽다","image_id":1}],"cropLabels":[],"images":[{"file_name":"책표지_사회과학_001682.jpg","date_created":"20210121","width":1600,"id":1,"height":1200}],"info":{"date_created":"20210121","name":"책표지_사회과학_001682","description":""},"metadata":[{"area":"","wordfont":"활자체","outline":"","illuminance":"","wordsize":"소","light":"","wordconnection":"빈공간없이 이어짐","subclass":"사회과학","weather":"","device":"스마트폰","wordcolor":"단색","class":"책표지","wordorientation":"가로"}]}