{"annotations":[{"bbox":[530,126,137,486],"id":1,"text":"한 권으로 읽는","image_id":1},{"bbox":[288,88,252,1080],"id":2,"text":"조선왕조실록","image_id":1},{"bbox":[837,0,87,256],"id":3,"text":"xxx","image_id":1},{"bbox":[135,6,53,250],"id":4,"text":"xxx","image_id":1},{"bbox":[131,254,50,339],"id":5,"text":"xxx","image_id":1},{"bbox":[97,6,38,243],"id":6,"text":"xxx","image_id":1},{"bbox":[106,249,27,162],"id":7,"text":"xxx","image_id":1},{"bbox":[60,1,33,310],"id":8,"text":"xxx","image_id":1},{"bbox":[4,8,53,370],"id":9,"text":"xxx","image_id":1}],"cropLabels":[],"images":[{"file_name":"책표지_역사_000073.jpg","date_created":"20210121","width":1600,"id":1,"height":1200}],"info":{"date_created":"20210121","name":"책표지_역사_000073","description":""},"metadata":[{"area":"","wordfont":"활자체","outline":"","illuminance":"","wordsize":"소","light":"","wordconnection":"빈공간으로 나뉨","subclass":"역사","weather":"","device":"스마트폰","wordcolor":"단색","class":"책표지","wordorientation":"세로"}]}