{"annotations":[{"bbox":[706,131,441,257],"id":1,"text":"xxx","image_id":1},{"bbox":[116,379,1414,286],"id":2,"text":"인생을 결정하는","image_id":1},{"bbox":[357,666,879,256],"id":3,"text":"열 가지 힘","image_id":1},{"bbox":[379,991,857,177],"id":4,"text":"xxx","image_id":1}],"cropLabels":[],"images":[{"file_name":"책표지_철학_001745.jpg","date_created":"20210210","width":1600,"id":1,"height":1200}],"info":{"date_created":"20210210","name":"책표지_철학_001745","description":""},"metadata":[{"area":"","wordfont":"활자체","outline":"","illuminance":"","wordsize":"중","light":"","wordconnection":"빈공간으로 나뉨","subclass":"철학","weather":"","device":"스마트폰","wordcolor":"단색","class":"책표지","wordorientation":"가로"}]}