{"annotations":[{"bbox":[339,425,843,166],"id":1,"text":"바그다드의","image_id":1},{"bbox":[260,608,1000,181],"id":2,"text":"프랑켄슈타인","image_id":1},{"bbox":[400,898,720,78],"id":3,"text":"아흐메드 사다위 장편소설","image_id":1},{"bbox":[596,1003,335,76],"id":4,"text":"조영학 옮김","image_id":1}],"cropLabels":[],"images":[{"file_name":"책표지_문학_006108.jpg","date_created":"20210206","width":1600,"id":1,"height":1200}],"info":{"date_created":"20210206","name":"책표지_문학_006108","description":""},"metadata":[{"area":"","wordfont":"활자체","outline":"","illuminance":"","wordsize":"중","light":"","wordconnection":"빈공간으로 나뉨","subclass":"문학","weather":"","device":"스마트폰","wordcolor":"단색","class":"책표지","wordorientation":"가로"}]}