{"annotations":[{"bbox":[105,902,828,219],"id":1,"text":"아메리카의","image_id":1},{"bbox":[964,895,471,216],"id":2,"text":"xxx","image_id":1},{"bbox":[1440,898,150,170],"id":3,"text":"xxx","image_id":1},{"bbox":[107,421,288,66],"id":4,"text":"xxx","image_id":1}],"cropLabels":[],"images":[{"file_name":"책표지_사회과학_000373.jpg","date_created":"20210206","width":1600,"id":1,"height":1200}],"info":{"date_created":"20210206","name":"책표지_사회과학_000373","description":""},"metadata":[{"area":"","wordfont":"활자체","outline":"","illuminance":"","wordsize":"대","light":"","wordconnection":"빈공간없이 이어짐","subclass":"사회과학","weather":"","device":"스마트폰","wordcolor":"단색","class":"책표지","wordorientation":"가로"}]}