{"annotations":[{"bbox":[346,12,777,427],"id":1,"text":"최신","image_id":1},{"bbox":[317,437,806,381],"id":2,"text":"공정","image_id":1},{"bbox":[317,816,1163,374],"id":3,"text":"관리론","image_id":1}],"cropLabels":[],"images":[{"file_name":"책표지_기술과학_001025.JPG","date_created":"20210205","width":1600,"id":1,"height":1200}],"info":{"date_created":"20210205","name":"책표지_기술과학_001025","description":""},"metadata":[{"area":"","wordfont":"활자체","outline":"","illuminance":"","wordsize":"중","light":"","wordconnection":"빈공간없이 이어짐","subclass":"기술과학","weather":"","device":"스마트폰","wordcolor":"여러색","class":"책표지","wordorientation":"가로"}]}