{"annotations":[{"bbox":[328,312,489,353],"id":1,"text":"진리","image_id":1},{"bbox":[798,420,197,221],"id":2,"text":"의","image_id":1},{"bbox":[997,269,580,392],"id":3,"text":"말씀","image_id":1},{"bbox":[106,712,492,292],"id":4,"text":"xxx","image_id":1},{"bbox":[591,734,235,264],"id":5,"text":"xxx","image_id":1},{"bbox":[822,666,536,307],"id":6,"text":"xxx","image_id":1},{"bbox":[725,1093,177,95],"id":7,"text":"xxx","image_id":1}],"cropLabels":[],"images":[{"file_name":"책표지_종교_000881.jpg","date_created":"20210122","width":1600,"id":1,"height":1200}],"info":{"date_created":"20210122","name":"책표지_종교_000881","description":""},"metadata":[{"area":"","wordfont":"활자체","outline":"","illuminance":"","wordsize":"소","light":"","wordconnection":"빈공간없이 이어짐","subclass":"종교","weather":"","device":"스마트폰","wordcolor":"단색","class":"책표지","wordorientation":"가로"}]}