{"annotations":[{"bbox":[269,24,1042,532],"id":1,"text":"질병","image_id":1},{"bbox":[265,552,1071,517],"id":2,"text":"완치","image_id":1},{"bbox":[26,552,122,91],"id":3,"text":"xxx","image_id":1},{"bbox":[1555,1,45,1199],"id":4,"text":"xxx","image_id":1}],"cropLabels":[],"images":[{"file_name":"책표지_기술과학_004414.jpg","date_created":"20210207","width":1600,"id":1,"height":1200}],"info":{"date_created":"20210207","name":"책표지_기술과학_004414","description":""},"metadata":[{"area":"","wordfont":"활자체","outline":"","illuminance":"","wordsize":"중","light":"","wordconnection":"빈공간없이 이어짐","subclass":"기술과학","weather":"","device":"스마트폰","wordcolor":"단색","class":"책표지","wordorientation":"가로"}]}