{"annotations":[{"bbox":[209,175,480,146],"id":1,"text":"이희수 교수의","image_id":1},{"bbox":[192,316,1370,253],"id":2,"text":"지중해 문화기행","image_id":1},{"bbox":[-13,176,72,520],"id":3,"text":"xxx","image_id":1},{"bbox":[766,799,768,184],"id":4,"text":"xxx","image_id":1}],"cropLabels":[],"images":[{"file_name":"책표지_역사_001132.JPG","date_created":"20210117","width":1600,"id":1,"height":1200}],"info":{"date_created":"20210117","name":"책표지_역사_001132","description":""},"metadata":[{"area":"","wordfont":"활자체","outline":"","illuminance":"","wordsize":"중","light":"","wordconnection":"빈공간으로 나뉨","subclass":"역사","weather":"","device":"스마트폰","wordcolor":"단색","class":"책표지","wordorientation":"가로"}]}