{"annotations":[{"bbox":[978,110,128,350],"id":1,"text":"히토미의","image_id":1},{"bbox":[994,464,157,636],"id":2,"text":"수채화로 만나는","image_id":1},{"bbox":[875,118,96,557],"id":3,"text":"xxx","image_id":1}],"cropLabels":[],"images":[{"file_name":"책표지_예술_000673.jpg","date_created":"20210202","width":1600,"id":1,"height":1200}],"info":{"date_created":"20210202","name":"책표지_예술_000673","description":""},"metadata":[{"area":"","wordfont":"활자체","outline":"","illuminance":"","wordsize":"소","light":"","wordconnection":"빈공간으로 나뉨","subclass":"예술","weather":"","device":"스마트폰","wordcolor":"단색","class":"책표지","wordorientation":"세로"}]}