{"annotations":[{"bbox":[585,292,157,152],"id":1,"text":"뼈","image_id":1},{"bbox":[787,288,339,179],"id":2,"text":"있는","image_id":1},{"bbox":[571,491,348,175],"id":3,"text":"아무","image_id":1},{"bbox":[959,504,199,154],"id":4,"text":"xxx","image_id":1},{"bbox":[462,684,696,224],"id":5,"text":"xxx","image_id":1}],"cropLabels":[],"images":[{"file_name":"책표지_기타_003016.jpg","date_created":"20210126","width":1600,"id":1,"height":1200}],"info":{"date_created":"20210126","name":"책표지_기타_003016","description":""},"metadata":[{"area":"","wordfont":"활자체","outline":"","illuminance":"","wordsize":"소","light":"","wordconnection":"빈공간없이 이어짐","subclass":"기타","weather":"","device":"스마트폰","wordcolor":"단색","class":"책표지","wordorientation":"가로"}]}