{"annotations":[{"bbox":[670,205,99,416],"id":1,"text":"너의췌장을먹고싶어","image_id":1},{"bbox":[774,205,52,282],"id":2,"text":"xxx","image_id":1},{"bbox":[665,1008,148,29],"id":3,"text":"xxx","image_id":1}],"cropLabels":[],"images":[{"file_name":"책표지_문학_005035.jpg","date_created":"20210127","width":1600,"id":1,"height":1200}],"info":{"date_created":"20210127","name":"책표지_문학_005035","description":""},"metadata":[{"area":"","wordfont":"활자체","outline":"","illuminance":"","wordsize":"중","light":"","wordconnection":"빈공간으로 나뉨","subclass":"문학","weather":"","device":"스마트폰","wordcolor":"단색","class":"책표지","wordorientation":"세로"}]}