{"annotations":[{"bbox":[107,254,368,101],"id":1,"text":"xxx","image_id":1},{"bbox":[474,264,423,91],"id":2,"text":"xxx","image_id":1},{"bbox":[109,353,896,206],"id":3,"text":"믿음의 마법","image_id":1},{"bbox":[1130,383,470,114],"id":4,"text":"xxx","image_id":1},{"bbox":[0,0,1593,249],"id":5,"text":"xxx","image_id":1}],"cropLabels":[],"images":[{"file_name":"책표지_철학_001318.jpg","date_created":"20210209","width":1600,"id":1,"height":1200}],"info":{"date_created":"20210209","name":"책표지_철학_001318","description":""},"metadata":[{"area":"","wordfont":"활자체","outline":"","illuminance":"","wordsize":"대","light":"","wordconnection":"빈공간으로 나뉨","subclass":"철학","weather":"","device":"스마트폰","wordcolor":"단색","class":"책표지","wordorientation":"가로"}]}