{"annotations":[{"bbox":[345,162,896,203],"id":1,"text":"xxx","image_id":1},{"bbox":[93,368,1393,396],"id":2,"text":"일기쓰기","image_id":1},{"bbox":[1249,1046,351,122],"id":3,"text":"xxx","image_id":1}],"cropLabels":[],"images":[{"file_name":"책표지_언어_001875.jpg","date_created":"20210204","width":1600,"id":1,"height":1200}],"info":{"date_created":"20210204","name":"책표지_언어_001875","description":""},"metadata":[{"area":"","wordfont":"활자체","outline":"","illuminance":"","wordsize":"중","light":"","wordconnection":"빈공간없이 이어짐","subclass":"언어","weather":"","device":"스마트폰","wordcolor":"단색","class":"책표지","wordorientation":"가로"}]}