{"annotations":[{"bbox":[265,204,1095,309],"id":1,"text":"말하자면","image_id":1},{"bbox":[278,523,237,350],"id":2,"text":"좋","image_id":1},{"bbox":[513,564,836,260],"id":3,"text":"은 사람","image_id":1},{"bbox":[282,947,426,194],"id":4,"text":"xxx","image_id":1}],"cropLabels":[],"images":[{"file_name":"책표지_문학_005541.jpg","date_created":"20210128","width":1600,"id":1,"height":1200}],"info":{"date_created":"20210128","name":"책표지_문학_005541","description":""},"metadata":[{"area":"","wordfont":"캘리그라피","outline":"","illuminance":"","wordsize":"소","light":"","wordconnection":"빈공간으로 나뉨","subclass":"문학","weather":"","device":"스마트폰","wordcolor":"단색","class":"책표지","wordorientation":"가로"}]}