{"annotations":[{"bbox":[283,273,292,132],"id":1,"text":"사랑의","image_id":1},{"bbox":[263,421,1227,271],"id":2,"text":"수화교실","image_id":1},{"bbox":[702,876,670,92],"id":3,"text":"한국청각장애자복지회","image_id":1},{"bbox":[1395,876,102,95],"id":4,"text":"xxx","image_id":1}],"cropLabels":[],"images":[{"file_name":"책표지_사회과학_000001.JPG","date_created":"20210115","width":1600,"id":1,"height":1200}],"info":{"date_created":"20210115","name":"책표지_사회과학_000001","description":""},"metadata":[{"area":"","wordfont":"활자체","outline":"","illuminance":"","wordsize":"소","light":"","wordconnection":"빈공간없이 이어짐","subclass":"사회과학","weather":"","device":"스마트폰","wordcolor":"단색","class":"책표지","wordorientation":"가로"}]}