{"annotations":[{"bbox":[537,385,816,811],"id":1,"text":"xxx","image_id":1},{"bbox":[365,203,288,69],"id":2,"text":"다시 나누고 싶은","image_id":1},{"bbox":[653,205,122,64],"id":3,"text":"이야기","image_id":1},{"bbox":[369,150,302,53],"id":4,"text":"xxx","image_id":1}],"cropLabels":[],"images":[{"file_name":"책표지_사회과학_000870.jpg","date_created":"20210206","width":1600,"id":1,"height":1200}],"info":{"date_created":"20210206","name":"책표지_사회과학_000870","description":""},"metadata":[{"area":"","wordfont":"활자체","outline":"","illuminance":"","wordsize":"소","light":"","wordconnection":"빈공간으로 나뉨","subclass":"사회과학","weather":"","device":"스마트폰","wordcolor":"단색","class":"책표지","wordorientation":"가로"}]}