{"annotations":[{"bbox":[88,728,499,350],"id":1,"text":"안녕","image_id":1},{"bbox":[676,746,886,357],"id":2,"text":"기독교","image_id":1},{"bbox":[978,1168,461,78],"id":3,"text":"xxx","image_id":1}],"cropLabels":[],"images":[{"file_name":"책표지_종교_002809.jpg","date_created":"20210117","width":1600,"id":1,"height":1200}],"info":{"date_created":"20210117","name":"책표지_종교_002809","description":""},"metadata":[{"area":"","wordfont":"활자체","outline":"","illuminance":"","wordsize":"중","light":"","wordconnection":"빈공간없이 이어짐","subclass":"종교","weather":"","device":"스마트폰","wordcolor":"단색","class":"책표지","wordorientation":"가로"}]}