{"annotations":[{"bbox":[12,12,313,439],"id":1,"text":"인","image_id":1},{"bbox":[323,46,313,419],"id":2,"text":"간","image_id":1},{"bbox":[632,86,248,343],"id":3,"text":"의","image_id":1},{"bbox":[942,108,272,348],"id":4,"text":"xxx","image_id":1},{"bbox":[1211,68,278,342],"id":5,"text":"xxx","image_id":1},{"bbox":[80,534,225,156],"id":6,"text":"xxx","image_id":1},{"bbox":[334,533,584,171],"id":7,"text":"xxx","image_id":1},{"bbox":[951,532,546,175],"id":8,"text":"xxx","image_id":1},{"bbox":[530,0,297,47],"id":9,"text":"xxx","image_id":1},{"bbox":[1067,5,75,54],"id":10,"text":"xxx","image_id":1},{"bbox":[48,1153,594,47],"id":11,"text":"xxx","image_id":1}],"cropLabels":[],"images":[{"file_name":"책표지_사회과학_000166.jpg","date_created":"20210206","width":1600,"id":1,"height":1200}],"info":{"date_created":"20210206","name":"책표지_사회과학_000166","description":""},"metadata":[{"area":"","wordfont":"활자체","outline":"","illuminance":"","wordsize":"대","light":"","wordconnection":"빈공간으로 나뉨","subclass":"사회과학","weather":"","device":"스마트폰","wordcolor":"단색","class":"책표지","wordorientation":"가로"}]}