{"annotations":[{"bbox":[683,207,545,213],"id":1,"text":"슬곰이네","image_id":1},{"bbox":[286,413,1048,357],"id":2,"text":"강아지","image_id":1},{"bbox":[346,770,958,405],"id":3,"text":"식탁","image_id":1}],"cropLabels":[],"images":[{"file_name":"책표지_기술과학_000935.JPG","date_created":"20210205","width":1600,"id":1,"height":1200}],"info":{"date_created":"20210205","name":"책표지_기술과학_000935","description":""},"metadata":[{"area":"","wordfont":"캘리그라피","outline":"","illuminance":"","wordsize":"중","light":"","wordconnection":"빈공간없이 이어짐","subclass":"기술과학","weather":"","device":"스마트폰","wordcolor":"여러색","class":"책표지","wordorientation":"가로"}]}